sta/__init__.py
sta/client.py
sta/definitions.py
sta/sta_client.py
sta/util.py
pysta-0.0.32.dist-info/LICENSE
pysta-0.0.32.dist-info/METADATA
pysta-0.0.32.dist-info/WHEEL
pysta-0.0.32.dist-info/top_level.txt
pysta-0.0.32.dist-info/RECORD
