Metadata-Version: 2.1
Name: pysta
Version: 0.0.32
Summary: Python SensorThings Client
Home-page: https://github.com/NMWDI/pysta
Author: Jake Ross
Classifier: Programming Language :: Python :: 3
Classifier: Operating System :: OS Independent
Requires-Python: >=3.6
License-File: LICENSE
Requires-Dist: Click
Requires-Dist: requests
Requires-Dist: jsonschema (==3)
Requires-Dist: pyyaml
